[
  {
    "slug": "digital-tools-organizing-research-thesis-2026",
    "title": "Master Your Research: Top Digital Tools for Academic Organization in 2026",
    "excerpt": "Learn how to streamline your research workflow with cutting-edge digital tools. From AI thesis generators to citation managers, transform your academic process.",
    "description": "Discover the best digital tools for organizing your research in 2026. Boost productivity with AI-powered solutions and proven thesis writing tips.",
    "date": "2026-02-02",
    "publishedAt": "2026-02-02T15:59:44.518Z",
    "author": "Thesis Generator Research Team",
    "category": "Technology",
    "tags": [
      "research organization",
      "academic tools",
      "thesis writing",
      "AI research",
      "productivity"
    ],
    "keywords": [
      "research paper generator",
      "thesis writing tips",
      "best AI thesis generator 2026",
      "digital research tools",
      "academic organization"
    ],
    "image": "https://images.unsplash.com/photo-1677442136019-21780ecad995?w=800&q=80",
    "readTime": "12 min read",
    "featured": false,
    "filename": "2026-02-02-digital-tools-organizing-research-thesis-2026.mdx"
  }
]